README.md
setup.cfg
setup.py
pgpyui/__init__.py
pgpyui/button.py
pgpyui/checkbox.py
pgpyui/radio.py
pgpyui/slider.py
pgpyui/textarea.py
pgpyui.egg-info/PKG-INFO
pgpyui.egg-info/SOURCES.txt
pgpyui.egg-info/dependency_links.txt
pgpyui.egg-info/requires.txt
pgpyui.egg-info/top_level.txt