Metadata-Version: 2.1
Name: pgpyui
Version: 0.1.3
Summary: The package is an add-on for Pygame to create a user interface on the screen.
Home-page: https://pypi.org/project/pgpyui/
Author: Memdved
Author-email: mixail.vilyukov@icloud.com
Project-URL: GitHub, https://github.com/Memdved
Keywords: ui gui pgpyui pygame
Classifier: Programming Language :: Python :: 3.10
Classifier: License :: OSI Approved :: MIT License
Classifier: Operating System :: OS Independent
Requires-Python: >=3.6
Requires-Dist: requests>=2.25.1
